plomtts/__init__.py
plomtts/client.py
plomtts/exceptions.py
plomtts/models.py
plomtts_client-1.0.0.dist-info/METADATA
plomtts_client-1.0.0.dist-info/WHEEL
plomtts_client-1.0.0.dist-info/top_level.txt
plomtts_client-1.0.0.dist-info/RECORD
